labelme2yolov7segmentation/__init__.py
labelme2yolov7segmentation/__main__.py
labelme2yolov7segmentation/datatypes.py
labelme2yolov7segmentation-2.0.5.dist-info/METADATA
labelme2yolov7segmentation-2.0.5.dist-info/WHEEL
labelme2yolov7segmentation-2.0.5.dist-info/entry_points.txt
labelme2yolov7segmentation-2.0.5.dist-info/RECORD
