Metadata-Version: 2.1
Name: labelme2yolov7segmentation
Version: 2.0.5
Summary: 
Home-page: https://github.com/Tlaloc-Es/labelme2yolov7segmentation
License: MIT
Author: Tlaloc-Es
Author-email: dev@tlaloc-es.com
Requires-Python: >=3.10,<4.0
Classifier: License :: OSI Approved :: MIT License
Classifier: Programming Language :: Python :: 3
Classifier: Programming Language :: Python :: 3.10
Classifier: Programming Language :: Python :: 3.11
Requires-Dist: albumentations (>=1.3.0,<2.0.0)
Requires-Dist: click
Requires-Dist: numpy
Requires-Dist: pydantic
Requires-Dist: pyyaml
Project-URL: Repository, https://github.com/Tlaloc-Es/labelme2yolov7segmentation
